.DS_Store
.gitattributes
LICENSE
README.md
pyproject.toml
setup.py
src/.DS_Store
src/common_utils.py
src/cruise_toolkit/__init__.py
src/cruise_toolkit/__main__.py
src/cruise_toolkit/add_cb_ub.py
src/cruise_toolkit/adjust_bc_umi.py
src/cruise_toolkit/barcode_split.py
src/cruise_toolkit/cbumi_counter.py
src/cruise_toolkit/cli.py
src/cruise_toolkit/common_utils.py
src/cruise_toolkit/cr_ur_align.py
src/cruise_toolkit/cruise.py
src/cruise_toolkit/dispatch.py
src/cruise_toolkit.egg-info/PKG-INFO
src/cruise_toolkit.egg-info/SOURCES.txt
src/cruise_toolkit.egg-info/dependency_links.txt
src/cruise_toolkit.egg-info/entry_points.txt
src/cruise_toolkit.egg-info/top_level.txt
tests/test_import.py