Metadata-Version: 2.1
Name: cruise-toolkit
Version: 1.0.0
Summary: Unified CLI wrapper for barcode/UMI & CR/UR tools
Home-page: https://github.com/dawangran/cruise-toolkit
Author: Dawn
Author-email: 605547565@qq.com
License: MIT
Project-URL: Homepage, https://github.com/dawangran/cruise-toolkit
Keywords: single-cell,UMI,barcode,cyclone,RNA
Classifier: Programming Language :: Python :: 3
Classifier: License :: OSI Approved :: MIT License
Classifier: Operating System :: OS Independent
Requires-Python: >=3.8
License-File: LICENSE
